saul/__init__.py
saul/__main__.py
saul/license.py
saul/licenses/0bsd.toml
saul/licenses/afl-3.0.toml
saul/licenses/agpl-3.0.toml
saul/licenses/apache-2.0.toml
saul/licenses/artistic-2.0.toml
saul/licenses/bsd-2-clause.toml
saul/licenses/bsd-3-clause-clear.toml
saul/licenses/bsd-3-clause.toml
saul/licenses/bsd-4-clause.toml
saul/licenses/bsl-1.0.toml
saul/licenses/cc-by-4.0.toml
saul/licenses/cc-by-sa-4.0.toml
saul/licenses/cc0-1.0.toml
saul/licenses/cecill-2.1.toml
saul/licenses/cern-ohl-p-2.0.toml
saul/licenses/cern-ohl-s-2.0.toml
saul/licenses/cern-ohl-w-2.0.toml
saul/licenses/ecl-2.0.toml
saul/licenses/epl-1.0.toml
saul/licenses/epl-2.0.toml
saul/licenses/eupl-1.1.toml
saul/licenses/eupl-1.2.toml
saul/licenses/gpl-2.0.toml
saul/licenses/gpl-3.0.toml
saul/licenses/isc.toml
saul/licenses/lgpl-2.1.toml
saul/licenses/lgpl-3.0.toml
saul/licenses/lppl-1.3c.toml
saul/licenses/mit-0.toml
saul/licenses/mit.toml
saul/licenses/mpl-2.0.toml
saul/licenses/ms-pl.toml
saul/licenses/ms-rl.toml
saul/licenses/mulanpsl-2.0.toml
saul/licenses/ncsa.toml
saul/licenses/odbl-1.0.toml
saul/licenses/ofl-1.1.toml
saul/licenses/osl-3.0.toml
saul/licenses/postgresql.toml
saul/licenses/unlicense.toml
saul/licenses/upl-1.0.toml
saul/licenses/vim.toml
saul/licenses/wtfpl.toml
saul/licenses/zlib.toml
saul-0.1.0.dist-info/LICENSE
saul-0.1.0.dist-info/METADATA
saul-0.1.0.dist-info/WHEEL
saul-0.1.0.dist-info/entry_points.txt
saul-0.1.0.dist-info/top_level.txt
saul-0.1.0.dist-info/RECORD
