Metadata-Version: 2.1
Name: saul
Version: 0.1.0
Summary: A simple license generator, based on choosealicense.com.
Home-page: https://github.com/kokkonisd/saul
Author: Dimitri Kokkonis
Author-email: kokkonisd@gmail.com
Classifier: License :: OSI Approved :: MIT License
Requires-Python: >=3.9
License-File: LICENSE
Requires-Dist: tomlkit
